showpyfigfonts/__init__.py
showpyfigfonts/__main__.py
showpyfigfonts-1.0.dist-info/METADATA
showpyfigfonts-1.0.dist-info/WHEEL
showpyfigfonts-1.0.dist-info/entry_points.txt
showpyfigfonts-1.0.dist-info/top_level.txt
showpyfigfonts-1.0.dist-info/RECORD
