Metadata-Version: 2.1
Name: showpyfigfonts
Version: 1.0
Summary: Alternative to showfigfonts for python
Author: Im Geek (Ankush Bhagat)
Author-email: <imegeek@gmail.com>
Keywords: python,pyfiglet,figlet,fonts,render
Classifier: Development Status :: 1 - Planning
Classifier: Intended Audience :: Developers
Classifier: Programming Language :: Python :: 3
Classifier: Operating System :: Unix
Classifier: Operating System :: MacOS :: MacOS X
Classifier: Operating System :: Microsoft :: Windows
Requires-Dist: pyfiglet
